saliencymetrics-0.30.dist-info/licenses/LICENSE
test/__init__.py
test/test_metrics.py
saliencymetrics-0.30.dist-info/METADATA
saliencymetrics-0.30.dist-info/WHEEL
saliencymetrics-0.30.dist-info/top_level.txt
saliencymetrics-0.30.dist-info/RECORD
