Metadata-Version: 2.4
Name: SaliencyMetrics
Version: 0.30
Summary: A collection of metrics for comparing saliency maps
Home-page: https://github.com/valevalerio/SaliencyMetrics
Author: Valerio Bonsignori
Author-email: Valerio Bonsignori <valerio.bonsignori@phd.unipi.it>
License-Expression: MIT
Project-URL: Homepage, https://github.com/valevalerio/SaliencyMetrics
Project-URL: Issues, https://github.com/valevalerio/SaliencyMetrics/issues
Classifier: Programming Language :: Python :: 3
Classifier: Operating System :: OS Independent
Requires-Python: >=3.10
License-File: LICENSE
Dynamic: author
Dynamic: home-page
Dynamic: license-file
Dynamic: requires-python
